memexllm/__init__.py
memexllm/algorithms/__init__.py
memexllm/algorithms/base.py
memexllm/algorithms/fifo.py
memexllm/core/__init__.py
memexllm/core/history.py
memexllm/core/models.py
memexllm/integrations/__init__.py
memexllm/integrations/openai.py
memexllm/storage/__init__.py
memexllm/storage/base.py
memexllm/storage/memory.py
memexllm/storage/sqlite.py
memexllm/types.py
memexllm/utils/__init__.py
memexllm/utils/exceptions.py
memexllm-0.1.0.dist-info/LICENSE
memexllm-0.1.0.dist-info/METADATA
memexllm-0.1.0.dist-info/WHEEL
memexllm-0.1.0.dist-info/RECORD
