Metadata-Version: 2.3
Name: memexllm
Version: 0.1.0
Summary: A library for managing LLM conversation history
License: MIT
Author: Ali Nabipour
Author-email: alinabipour01@gmail.com
Requires-Python: >=3.10
Classifier: Development Status :: 3 - Alpha
Classifier: Intended Audience :: Developers
Classifier: License :: OSI Approved :: MIT License
Classifier: Programming Language :: Python :: 3
Classifier: Programming Language :: Python :: 3.10
Classifier: Programming Language :: Python :: 3.11
Provides-Extra: sqlite
Requires-Dist: aiosqlite (>=0.19.0) ; extra == "sqlite"
Requires-Dist: pydantic (>=2.0.0,<3.0.0)
Requires-Dist: typing-extensions (>=4.0.0,<5.0.0)
Project-URL: Repository, https://github.com/eyenpi/memexllm
